main.py
setup.py
music_source_separation.egg-info/PKG-INFO
music_source_separation.egg-info/SOURCES.txt
music_source_separation.egg-info/dependency_links.txt
music_source_separation.egg-info/requires.txt
music_source_separation.egg-info/top_level.txt